MANIFEST.in
README.rst
bootstrap.py
buildout.cfg
setup.py
collective/__init__.py
collective.galleriffic.egg-info/PKG-INFO
collective.galleriffic.egg-info/SOURCES.txt
collective.galleriffic.egg-info/dependency_links.txt
collective.galleriffic.egg-info/entry_points.txt
collective.galleriffic.egg-info/namespace_packages.txt
collective.galleriffic.egg-info/not-zip-safe
collective.galleriffic.egg-info/requires.txt
collective.galleriffic.egg-info/top_level.txt
collective/galleriffic/__init__.py
collective/galleriffic/configure.zcml
collective/galleriffic/display_mode_1.pt
collective/galleriffic/display_mode_2.pt
collective/galleriffic/display_mode_3.pt
collective/galleriffic/interfaces.py
collective/galleriffic/rebuild_i18n.sh
collective/galleriffic/tests.py
collective/galleriffic/view.pt
collective/galleriffic/view.py
collective/galleriffic/css/caption.png
collective/galleriffic/css/display_mode_1.css
collective/galleriffic/css/display_mode_2.css
collective/galleriffic/css/display_mode_3.css
collective/galleriffic/css/loader.gif
collective/galleriffic/css/pause.png
collective/galleriffic/css/play.png
collective/galleriffic/css/step_backward.png
collective/galleriffic/css/step_forward.png
collective/galleriffic/locales/collective.galleriffic.pot
collective/galleriffic/locales/en/LC_MESSAGES/collective.galleriffic.po
collective/galleriffic/locales/fr/LC_MESSAGES/collective.galleriffic.po
collective/galleriffic/profiles/default/browserlayer.xml
collective/galleriffic/profiles/default/metadata.xml
collective/galleriffic/profiles/default/types/Folder.xml
collective/galleriffic/profiles/default/types/Link.xml
collective/galleriffic/profiles/default/types/Topic.xml
docs/HISTORY.txt
docs/INSTALL.txt
docs/LICENSE.GPL
docs/LICENSE.txt