Metadata-Version: 1.1
Name: collective.galleriffic
Version: 1.1.5
Summary: Galleriffic integration into Plone
Home-page: https://github.com/collective/collective.galleriffic
Author: JeanMichel FRANCOIS aka toutpt
Author-email: toutpt@gmail.com
License: GPL
Platform: UNKNOWN
Classifier: Framework :: Plone
Classifier: Framework :: Plone :: 4.0
Classifier: Framework :: Plone :: 4.1
Classifier: Programming Language :: Python
